{"contents":[{"imgSrc":[],"tagName":"H1","content":"UNIT 02 面试话题 Interview Topics"},{"imgSrc":[],"tagName":"H2","content":"Lesson 4 在校表现 Performance in School"},{"imgSrc":["https://res.weread.qq.com/wrepub/epub_26796696_207"],"tagName":"DIV","content":""},{"imgSrc":[],"tagName":"P","content":"场景对话"},{"imgSrc":[],"tagName":"P","content":""},{"imgSrc":[],"tagName":"P","content":"面试官苏珊在询问玛丽的在校表现。"},{"imgSrc":[],"tagName":"P","content":"Mary: What do you want to know about me?"},{"imgSrc":[],"tagName":"P","content":""},{"imgSrc":["https://res.weread.qq.com/wrepub/epub_26796696_208"],"tagName":"P","content":"Susan: How about your academic records at college?"},{"imgSrc":[],"tagName":"P","content":"苏珊：你在大学期间的学习成绩怎么样？"},{"imgSrc":[],"tagName":"P","content":""},{"imgSrc":[],"tagName":"P","content":"Mary: The average grade of all my courses is above 85."},{"imgSrc":[],"tagName":"P","content":"玛丽：我各科的平均成绩都在85分以上。"},{"imgSrc":[],"tagName":"P","content":""},{"imgSrc":["https://res.weread.qq.com/wrepub/epub_26796696_208"],"tagName":"P","content":"Susan: In which subject did you get the highest marks?"},{"imgSrc":[],"tagName":"P","content":"苏珊：你哪一科的成绩最好？"},{"imgSrc":[],"tagName":"DIV","content":"\\r\\n    职场达人小技巧\\r\\n\\r\\n    关于在校表现\\r\\n\\r\\n    在面试过程中，面试官有可能会问求职者的在校表现，这时求职者就不能把说话的重点仅仅放在在校成绩上，也要有侧重地说一些其他相关的话题。\\r\\n"},{"imgSrc":[],"tagName":"P","content":"Mary: In mathematics I got a 98."},{"imgSrc":[],"tagName":"P","content":""},{"imgSrc":["https://res.weread.qq.com/wrepub/epub_26796696_208"],"tagName":"P","content":"Susan: Have you received any scholarships?"},{"imgSrc":[],"tagName":"P","content":"苏珊：你获得过奖学金吗？"},{"imgSrc":[],"tagName":"P","content":""},{"imgSrc":[],"tagName":"P","content":"Mary: Yes, I have, and three times in total."},{"imgSrc":[],"tagName":"P","content":""},{"imgSrc":["https://res.weread.qq.com/wrepub/epub_26796696_208"],"tagName":"P","content":"Susan: Have you been a class leader?"},{"imgSrc":[],"tagName":"P","content":"苏珊：你当过班干部吗？"},{"imgSrc":[],"tagName":"P","content":""},{"imgSrc":[],"tagName":"P","content":"Mary: I have been a class commissary in charge of studies for two years."},{"imgSrc":[],"tagName":"P","content":""},{"imgSrc":["https://res.weread.qq.com/wrepub/epub_26796696_208"],"tagName":"P","content":"Susan: Did you join in any club activities?"},{"imgSrc":[],"tagName":"P","content":"苏珊：你参加社团活动吗？"},{"imgSrc":[],"tagName":"DIV","content":"\\r\\n    如果求职者在校成绩比较优秀，可以详细描述一下，以证明自己的努力和获得的成就，但是如果成绩不理想，还是应当尽量避免提及，一句话带过比较好。除了成绩，求职者还可以说明自己在其他方面的表现，比如，获得了某方面的专业资格证书，获得过奖学金或某种奖励，有没有当过学生干部或参加过什么实践活动等情况。\\r\\n"},{"imgSrc":[],"tagName":"P","content":"Mary: I was an aerobics team member in college."},{"imgSrc":[],"tagName":"P","content":""},{"imgSrc":["https://res.weread.qq.com/wrepub/epub_26796696_208"],"tagName":"P","content":"Susan: What sport are you good at?"},{"imgSrc":[],"tagName":"P","content":"苏珊：你最擅长的体育项目是什么？"},{"imgSrc":[],"tagName":"P","content":""},{"imgSrc":[],"tagName":"P","content":"Mary: I am good at sprint and table tennis."},{"imgSrc":[],"tagName":"P","content":""},{"imgSrc":["https://res.weread.qq.com/wrepub/epub_26796696_208"],"tagName":"P","content":"Susan: You are excellent."},{"imgSrc":[],"tagName":"P","content":"苏珊：你非常优秀。"},{"imgSrc":[],"tagName":"DIV","content":"\\r\\n    许多面试官往往会喜欢参加过很多实践活动的求职者，他们觉得这样的人会比较容易融入集体，实际操作能力也比较强，并不是个只会读书学习的人。因此求职者在这方面可以多说一些，以便加深面试官的印象。\\r\\n"},{"imgSrc":[],"tagName":"P","content":"必背例句"},{"imgSrc":[],"tagName":"P","content":"1.I am very interested in knowing about your performance in school."},{"imgSrc":[],"tagName":"P","content":"我很想了解一下你在学校的表现情况。"},{"imgSrc":[],"tagName":"P","content":"2.I have been an excellent student both in character and in learning since middle school."},{"imgSrc":[],"tagName":"P","content":"我从上中学起就一直是个品学兼优的好学生。"},{"imgSrc":[],"tagName":"P","content":"3.My records in school are excellent．我在学校期间的成绩很优秀。"},{"title":"我在大学期间多次获得奖学金。","answer":"I got scholarships several times in college．","describe":null},{"imgSrc":[],"tagName":"P","content":"5.My scores ranked the second in the class．我的成绩在全班排第二名。"},{"title":"我的英语成绩总是在90分以上。","answer":"My English grades were always above 90．","describe":null},{"imgSrc":[],"tagName":"P","content":"7.I have often taken part in club activities in college."},{"imgSrc":[],"tagName":"P","content":"我在大学期间经常参加社团活动。"},{"imgSrc":[],"tagName":"P","content":"8.I often won in sports competitions organized by our school."},{"imgSrc":[],"tagName":"P","content":"我经常在学校组织的体育比赛中获奖。"},{"imgSrc":[],"tagName":"P","content":"9.I participated in the English club in college."},{"imgSrc":[],"tagName":"P","content":"我在大学期间参加了英语俱乐部。"},{"imgSrc":[],"tagName":"P","content":"10.In college I did several part-time jobs to support myself."},{"imgSrc":[],"tagName":"P","content":"大学期间我做了好几份兼职工作来维持生活。"},{"imgSrc":[],"tagName":"P","content":""},{"imgSrc":[],"tagName":"P","content":"核心词汇总"},{"word":"performance","yinbiao":"[pə'fɔ:məns]","hanyi":"n. 表现"},{"word":"average","yinbiao":"['ævəridʒ]","hanyi":"adj. 平均的"},{"word":"mark","yinbiao":"[mɑ:k]","hanyi":"n. 分数"},{"word":"mathematics","yinbiao":"[ˌmæθi'mætiks]","hanyi":"n. 数学"},{"word":"scholarship","yinbiao":"['skɔləʃip]","hanyi":"n. 奖学金"},{"imgSrc":[],"tagName":"P","content":"in total 总共，总计"},{"word":"club","yinbiao":"[klʌb]","hanyi":"n. 社团，俱乐部"},{"word":"aerobics","yinbiao":"[ɛə'rəubiks]","hanyi":"n. 健美操"},{"word":"sprint","yinbiao":"[sprint]","hanyi":"n. 短跑"},{"imgSrc":[],"tagName":"P","content":"table tennis 乒乓球"},{"word":"character","yinbiao":"['kæriktə]","hanyi":"n. 品质"},{"word":"rank","yinbiao":"[ræŋk]","hanyi":"v. 排名"},{"imgSrc":[],"tagName":"P","content":"part time兼职"},{"imgSrc":[],"tagName":"P","content":"full time 全职"},{"imgSrc":[],"tagName":"P","content":"top student尖子生"},{"word":"class","yinbiao":"[klɑ:s]","hanyi":"n. 班级"},{"word":"department","yinbiao":"[di'pɑ:tmənt]","hanyi":"n. 系，部门"},{"word":"participate","yinbiao":"[pɑ:'tisipeit]","hanyi":"v. 参加"},{"word":"extracurricular","yinbiao":"[ˌekstrəkə'rikjulə]","hanyi":"adj. 课外的"}]}